radbelt/paths.py
radbelt/util.py
radbelt/core.cpython-312-darwin.so
radbelt/__init__.py
radbelt/.dylibs/libgfortran.5.dylib
radbelt/.dylibs/libquadmath.0.dylib
radbelt/.dylibs/libgcc_s.1.1.dylib
radbelt/extern/igrf/dgrf1965.dat
radbelt/extern/igrf/dgrf1970.dat
radbelt/extern/igrf/dgrf1960.dat
radbelt/extern/igrf/dgrf1975.dat
radbelt/extern/igrf/dgrf2015.dat
radbelt/extern/igrf/dgrf2000.dat
radbelt/extern/igrf/dgrf2010.dat
radbelt/extern/igrf/dgrf2005.dat
radbelt/extern/igrf/igrf2020.dat
radbelt/extern/igrf/igrf2020s.dat
radbelt/extern/igrf/dgrf1990.dat
radbelt/extern/igrf/dgrf1985.dat
radbelt/extern/igrf/dgrf1950.dat
radbelt/extern/igrf/dgrf1945.dat
radbelt/extern/igrf/dgrf1955.dat
radbelt/extern/igrf/dgrf1995.dat
radbelt/extern/igrf/dgrf1980.dat
radbelt/extern/aep8/ap8max.asc
radbelt/extern/aep8/ae8max.asc
radbelt/extern/aep8/ap8min.asc
radbelt/extern/aep8/ae8min.asc
radbelt-0.1.8.dist-info/RECORD
radbelt-0.1.8.dist-info/WHEEL
radbelt-0.1.8.dist-info/METADATA
