Metadata-Version: 2.1
Name: radbelt
Version: 0.1.8
Summary: Astropy-friendly wrapper for the AE-8/AP-8 Van Allen belt model
Author-Email: Leo Singer <leo.p.singer@nasa.gov>
License: NOSA
Classifier: Development Status :: 3 - Alpha
Classifier: Intended Audience :: Science/Research
Classifier: License :: OSI Approved
Classifier: Operating System :: MacOS
Classifier: Operating System :: Microsoft :: Windows
Classifier: Operating System :: POSIX
Classifier: Operating System :: POSIX :: Linux
Classifier: Operating System :: Unix
Classifier: Programming Language :: Python :: 3 :: Only
Classifier: Programming Language :: Python :: 3.9
Classifier: Programming Language :: Python :: 3.10
Classifier: Programming Language :: Python :: 3.11
Classifier: Programming Language :: Python :: 3.12
Classifier: Topic :: Scientific/Engineering :: Astronomy
Project-URL: Source, https://github.com/nasa/radbelt
Requires-Python: >=3.9
Requires-Dist: astropy
Requires-Dist: numpy>=1.19
Requires-Dist: pytest-doctestplus; extra == "test"
Provides-Extra: test
